whampyr/__init__.py
whampyr/whampyr.py
whampyr-0.1.0.dist-info/METADATA
whampyr-0.1.0.dist-info/RECORD
whampyr-0.1.0.dist-info/WHEEL
whampyr-0.1.0.dist-info/top_level.txt
