Metadata-Version: 2.1
Name: whampyr
Version: 0.1.0
Summary: Python clone of WHAMP
Home-page: https://github.com/jeandet/whampyr
Author: Alexis Jeandet
Author-email: alexis.jeandet@lpp.polytechnique.fr
License: GNU General Public License v3
Keywords: whampyr
Platform: UNKNOWN
Classifier: Development Status :: 2 - Pre-Alpha
Classifier: Intended Audience :: Developers
Classifier: License :: OSI Approved :: GNU General Public License v3 (GPLv3)
Classifier: Natural Language :: English
Classifier: Programming Language :: Python :: 2
Classifier: Programming Language :: Python :: 2.7
Classifier: Programming Language :: Python :: 3
Classifier: Programming Language :: Python :: 3.4
Classifier: Programming Language :: Python :: 3.5
Classifier: Programming Language :: Python :: 3.6
Requires-Dist: PyQt5
Requires-Dist: PyOpenGL
Requires-Dist: pyqtgraph
Requires-Dist: numpy
